zrna/__init__.py
zrna/__version__.py
zrna/api.py
zrna/update_firmware.py
zrna/util.py
zrna/zr_pb2.py
zrna-1.0.8.dist-info/LICENSE
zrna-1.0.8.dist-info/METADATA
zrna-1.0.8.dist-info/WHEEL
zrna-1.0.8.dist-info/top_level.txt
zrna-1.0.8.dist-info/RECORD
