Metadata-Version: 2.1
Name: zrna
Version: 1.0.8
Summary: API client for the Zrna software-defined analog platform.
Home-page: https://github.com/zrna-research/zrna-api
Author: Nicolas Steven Miller
Author-email: nicolas@zrna.org
License: APACHE
Platform: UNKNOWN
Classifier: License :: OSI Approved :: Apache Software License
Classifier: Programming Language :: Python :: 2
Classifier: Programming Language :: Python :: 2.7
Classifier: Programming Language :: Python :: 3
Classifier: Programming Language :: Python :: 3.6
Requires-Python: >=2.7, !=3.0.*, !=3.1.*, !=3.2.*, !=3.3.*, !=3.4.*, !=3.5.*, <4
Requires-Dist: cobs
Requires-Dist: future
Requires-Dist: inflection
Requires-Dist: protobuf
Requires-Dist: pyserial
